broadpy/__init__.py
broadpy/broad1.py
broadpy/broad3.py
broadpy/broad_base.py
broadpy/requirements.txt
broadpy/docs/images/broadpy.png
broadpy/util/__init__.py
broadpy/util/logger.py
broadpy-0.1.0.dist-info/METADATA
broadpy-0.1.0.dist-info/WHEEL
broadpy-0.1.0.dist-info/licenses/LICENSE.txt
broadpy-0.1.0.dist-info/RECORD
