Metadata-Version: 2.4
Name: broadpy
Version: 0.1.0
Summary: BRoaD API package
Project-URL: Homepage, https://github.com/BeeBeansTechnologies/BRoaDpy
Author-email: Bee Beans Technologies <sitcp@bbtech.co.jp>
License-File: LICENSE.txt
Classifier: License :: OSI Approved :: MIT License
Classifier: Operating System :: OS Independent
Classifier: Programming Language :: Python :: 3
Requires-Python: >=3.9
Requires-Dist: sitcpy>=0.1.1
